{"id": "1264", "title": "Slideshow", "explainurl": "https://explainxkcd.com/wiki/index.php/1264%3A%20Slideshow", "characters": ["Cueball"], "alt": "Points to anyone who hacks the Flickr devs' computers to make their text editors do this when you click on anything.", "image_url": "https://imgs.xkcd.com/comics/slideshow.gif", "year": 2013, "month": 9, "day": 13, "transcript": "Dear website operators,\n[This strip is in the form of an animated gif. The panels transition with a Ken Burns-like fade-and-pan.]\n[Cueball's whole body on the left side of the panel, looking slightly right of the camera.]\nCueball: I will never...\n[Cueball's body down to the ends of his arms is shown on the right side of the panel, looking slightly left of the camera.]\nCueball: ...want to browse a series of images...\n[Cueball is shown standing in the middle of the panel, with his left hand up a little bit.\nCueball: ...like this.", "explanation": "It is very common for websites to feature a gallery of images \u2013\u00a0a website for a school, for example, might feature pictures of the students and teachers. Some websites display images in the form of a slideshow like this comic, with slow zoom and pan effects and fades between the images. This effect has been dubbed the  after documentary filmmaker  who popularized the effect. In many cases, the slideshow is a fixed element, and can't be controlled by the user. This prevents the user from navigating through the images at their own pace or viewing any one image for an extended period, and can be distracting. Randall expresses frustration at this.\n\nThe title text suggests points will be awarded to whoever can add that annoying effect to the text editors of the developers of , a photo-hosting website, so they can be subjected to the same thing to which they are subjecting Randall. This may be a response to recent changes to Flickr's website that includes such slideshows as one option; that said, Flickr has always allowed users to browse galleries in a normal grid layout and with user-controlled photo-by-photo full-window layout.\n\n", "complete": true}