{"id": "15", "title": "Just Alerting You", "explainurl": "https://explainxkcd.com/wiki/index.php/15%3A%20Just%20Alerting%20You", "characters": [], "alt": "Just thought you should know", "image_url": "https://imgs.xkcd.com/comics/just_alerting_you.jpg", "year": 2006, "month": 1, "day": 1, "transcript": "[A person is standing on the back of a green dinosaur and holding reins to the dinosaur's head.]\nPerson: Before you talk to me, I should warn you: I am kind of strange", "explanation": "In this comic, a person is riding a  (or what would later be referred to as an ). The humor lies in the fact that the person feels the need to highlight their peculiarity, despite the obvious oddity of riding an extinct and dangerous creature. Megan would later imagine riding an Apatosaurus in 650: Nowhere. This dinosaur genus is also mentioned in 460: Paleontology and 636: Brontosaurus. This was the first comic to feature a dinosaur, but since then, there have been numerous comics about them on xkcd.\n\nThe title text further emphasizes this, while the original caption signifies that Randall would start posting a new comic every Monday, Wednesday, and Friday. Ironically enough, this comic was posted on a Sunday, a few minutes before Monday: see the trivia section. From now, he also began putting the date into most, but not all, comic titles on LiveJournal until he started to use xkcd.com instead.\n\n", "complete": true}