{"id": "158", "title": "Six Months", "explainurl": "https://explainxkcd.com/wiki/index.php/158%3A%20Six%20Months", "characters": ["Cueball"], "alt": "But then she does that thing with her tongue and I remember why I left you.", "image_url": "https://imgs.xkcd.com/comics/six_months.png", "year": 2006, "month": 9, "day": 18, "transcript": "[Cueball is standing.]\nCueball: It's been six months and I still have those dreams where you're pressed tight against me, where you look into my eyes and give me that grin and it's like you've forgotten everything.\n\nCueball: And something in the back of my head says it's wrong, it's not like this anymore, but I push it down.  In the morning, I tell myself I can't control my dreams, but there's a part of me that doesn't want them to stop.\n\nCueball: And honestly, waking up would be a lot easier if your mom didn't look so much like you.\nCueball: There's always that moment of confusion.", "explanation": "\nCueball is addressing his ex-partner, telling her that six months after their split-up, he still has dreams of them being together. In the moment after waking up, he is sometimes unable to tell reality and dream apart. However, the third panel reveals the punchline: His confusion results from the likeness between his ex and her mother, next to whom he apparently wakes up every morning. It becomes clear that he has left the girl six months ago in order to live with her mother instead. The comic lampshades at the state of emotional confusion after a break-up that is prominently featured in many films and books.\n\nThe title text furthers the joke, saying the confusion of why he left her is gone once the older woman does \"that thing with her tongue,\" possibly referring to fellatio.\n\n", "complete": true}