{"id": "334", "title": "Wasteland", "explainurl": "https://explainxkcd.com/wiki/index.php/334%3A%20Wasteland", "characters": ["Cueball"], "alt": "You make forgetting look so easy.", "image_url": "https://imgs.xkcd.com/comics/wasteland.png", "year": 2007, "month": 10, "day": 26, "transcript": "[Cueball is walking through a wasteland talking to himself.]\nCueball: I am alone in this wasteland, a thousand miles from you.\nCueball: But I haven't forgotten the feel of your skin, your mischievous smile.\nCueball: You'd think a thousand miles would be enough.\nCueball: I guess I'll keep walking.", "explanation": "At the beginning of the comic, Cueball is wandering around in a barren area, supposedly a desert, thinking about his ex-partner, in which he, at first, appears to be fondly remembering them, but the last two boxes explain that he is trying to take a long walk to forget them, and is obviously not very good at it.\n\nThe title text implies that his ex-partner had easily forgotten him, and he wishes that he could forget more easily. It's also possible that he means that it's so hard to forget them that forgetting anything else is simple in comparison to it.\n\nThere is a similar twist in comics 71: In the Trees and 1042: Never.\n\n", "complete": true}