{"id": "858", "title": "Milk", "explainurl": "https://explainxkcd.com/wiki/index.php/858%3A%20Milk", "characters": ["Cueball", "Megan"], "alt": "It's not hard when you have the same thought like 40 or 50 percent of the time.", "image_url": "https://imgs.xkcd.com/comics/milk.png", "year": 2011, "month": 2, "day": 9, "transcript": "[Couple sitting opposed, Megan on couch reading book and Cueball a chair with a laptop.]\nMegan: The fact that I have breasts doesn't mean you could milk me now. I'd have to be lactating.\n[A beat passes.]\n [In the third panel, Megan's legs are not seen, probably tucked under the armchair to feel more secure.]\nCueball (thinking): Oh my god she's psychic.", "explanation": "Megan and Cueball are sitting quietly, engaged in their own solo pursuits.  Without any preamble, Megan answers a question that has not been asked, pointing out to Cueball that he would not be able to obtain milk from her breasts right now, as she is not .  Cueball is flabbergasted that she seems to have read his mind, as this was exactly what he was wondering.\n\nMegan, like any healthy adult female , is capable of producing milk from her . She does not need to be pregnant in order to lactate; some women are able to lactate before getting pregnant, but being pregnant will increase the chances of her being able to lactate.\n\nThe title text indicates that this is not proof of Megan's psychic powers, as Cueball seems quite obsessed with this particular topic, although, if you interpret it as a response to Cueball's thoughts in the last panel it could remain ambiguous.\nAlternatively it could mean that Megan and Cueball are having the same thoughts 40 or 50% of the time and thus it's actually easy for her (or actually both) to guess his thoughts.\n\n", "complete": true}